.gitignore
README.rst
setup.py
TxScheduling.egg-info/PKG-INFO
TxScheduling.egg-info/SOURCES.txt
TxScheduling.egg-info/dependency_links.txt
TxScheduling.egg-info/not-zip-safe
TxScheduling.egg-info/requires.txt
TxScheduling.egg-info/top_level.txt
docs/CONTRIBUTORS.rst
docs/HISTORY.rst
docs/LICENSE
txscheduling/__init__.py
txscheduling/cron.py
txscheduling/interfaces.py
txscheduling/task.py
txscheduling/tests/__init__.py
txscheduling/tests/cron.py
txscheduling/tests/task.py