Metadata-Version: 1.0
Name: TxScheduling
Version: 1.1
Summary: A scheduling plugin for Twisted
Home-page: https://github.com/benliles/TxScheduling
Author: Benjamin Liles
Author-email: benliles@gmail.com
License: UNKNOWN
Keywords: twisted python scheduling cron
Platform: UNKNOWN
Classifier: Programming Language :: Python
Classifier: Framework :: Twisted
Classifier: Development Status :: 4 - Beta
Classifier: Intended Audience :: Developers
Classifier: License :: OSI Approved :: Apache Software License
Classifier: Topic :: Software Development :: Libraries :: Application Frameworks
Classifier: Topic :: Software Development :: Libraries :: Python Modules
